{
  "products": [
    {
      "id": "8345739722809",
      "name": "Rustic Solid Wood Bed with Sculptural Branch Headboard",
      "handle": "rustic-solid-wood-platform-bed-tree-branch-headboard-b0h7bd65d7",
      "missing_variant_type": "true",
      "wrong_description": "true",
      "imported_at": ""
    },
    {
      "id": "8345739690041",
      "name": "Rustic Solid Wood Bed with Sculptural Branch Headboard",
      "handle": "rustic-solid-wood-platform-bed-tree-branch-headboard-b0h7bd2cwj",
      "missing_variant_type": "true",
      "wrong_description": "true",
      "imported_at": ""
    },
    {
      "id": "8345739657273",
      "name": "Rustic Solid Wood Bed with Sculptural Branch Headboard",
      "handle": "rustic-solid-wood-platform-bed-tree-branch-headboard-b0h7b5b3jg",
      "missing_variant_type": "true",
      "wrong_description": "true",
      "imported_at": ""
    },
    {
      "id": "8345739624505",
      "name": "Rustic Solid Wood Bed with Sculptural Branch Headboard",
      "handle": "rustic-solid-wood-platform-bed-tree-branch-headboard-b0h7b833df",
      "missing_variant_type": "true",
      "wrong_description": "true",
      "imported_at": ""
    },
    {
      "id": "8345739591737",
      "name": "Rustic Solid Wood Bed with Sculptural Branch Headboard",
      "handle": "rustic-solid-wood-platform-bed-tree-branch-headboard-b0h6fgxkz7",
      "missing_variant_type": "true",
      "wrong_description": "true",
      "imported_at": ""
    },
    {
      "id": "8346020282425",
      "name": "Modern Solid Wood Vinyl Record Storage Console Stand",
      "handle": "modern-solid-wood-vinyl-record-storage-cabinet-stand",
      "missing_variant_type": "true",
      "wrong_description": "true",
      "imported_at": "2026-07-18T03:02:33Z"
    },
    {
      "id": "8346048888889",
      "name": "Modern Wooden Record Stand with Turntable Storage Shelf",
      "handle": "modern-wooden-record-stand-turntable-storage-shelf",
      "missing_variant_type": "true",
      "wrong_description": "true",
      "imported_at": "2026-07-18T05:36:07Z"
    }
  ]
}
